{
  "timestamp": "2025-10-30T04:26:39.170685",
  "target_path": "src/core/business_process",
  "metrics": {
    "total_files": 18,
    "total_lines": 5651,
    "total_patterns": 345,
    "refactor_opportunities": 167
  },
  "quality_score": 0.858,
  "overall_score": 0.8645999999999999,
  "risk_assessment": {
    "overall_risk": "very_high",
    "risk_breakdown": {
      "low": 126,
      "high": 41
    },
    "severity_breakdown": {
      "medium": 142,
      "high": 4,
      "low": 21
    },
    "automated_opportunities": 55,
    "manual_opportunities": 112
  },
  "opportunities": [
    {
      "opportunity_id": "long_function___init___5247489382654986553",
      "title": "长函数重构: __init__",
      "description": "函数 __init__ 过长 (56 行)，建议拆分为更小的函数",
      "severity": "medium",
      "confidence": 0.85,
      "effort": "medium",
      "impact": "maintainability",
      "file_path": "src\\core\\business_process\\optimizer\\optimizer_refactored.py",
      "line_number": 85,
      "code_snippet": "def __init__(...):  # 56 lines",
      "suggested_fix": "将函数拆分为多个职责单一的函数",
      "risk_level": "low",
      "automated": false
    },
    {
      "opportunity_id": "large_class_IntelligentBusinessProcessOptimizer_5247489382654986553",
      "title": "大类重构: IntelligentBusinessProcessOptimizer",
      "description": "类 IntelligentBusinessProcessOptimizer 过大 (310 行)，违反单一职责原则",
      "severity": "high",
      "confidence": 0.8,
      "effort": "high",
      "impact": "maintainability",
      "file_path": "src\\core\\business_process\\optimizer\\optimizer_refactored.py",
      "line_number": 62,
      "code_snippet": "class IntelligentBusinessProcessOptimizer:  # 310 lines",
      "suggested_fix": "将类拆分为多个职责单一的类",
      "risk_level": "high",
      "automated": false
    },
    {
      "opportunity_id": "large_class_ProcessMonitor_1154821944592946160",
      "title": "大类重构: ProcessMonitor",
      "description": "类 ProcessMonitor 过大 (313 行)，违反单一职责原则",
      "severity": "high",
      "confidence": 0.8,
      "effort": "high",
      "impact": "maintainability",
      "file_path": "src\\core\\business_process\\optimizer\\components\\process_monitor.py",
      "line_number": 54,
      "code_snippet": "class ProcessMonitor:  # 313 lines",
      "suggested_fix": "将类拆分为多个职责单一的类",
      "risk_level": "high",
      "automated": false
    },
    {
      "opportunity_id": "large_class_RecommendationGenerator_-5947762189228750654",
      "title": "大类重构: RecommendationGenerator",
      "description": "类 RecommendationGenerator 过大 (305 行)，违反单一职责原则",
      "severity": "high",
      "confidence": 0.8,
      "effort": "high",
      "impact": "maintainability",
      "file_path": "src\\core\\business_process\\optimizer\\components\\recommendation_generator.py",
      "line_number": 63,
      "code_snippet": "class RecommendationGenerator:  # 305 lines",
      "suggested_fix": "将类拆分为多个职责单一的类",
      "risk_level": "high",
      "automated": false
    },
    {
      "opportunity_id": "large_class_MarketAnalyzer_192957834875483427",
      "title": "大类重构: MarketAnalyzer",
      "description": "类 MarketAnalyzer 过大 (388 行)，违反单一职责原则",
      "severity": "high",
      "confidence": 0.8,
      "effort": "high",
      "impact": "maintainability",
      "file_path": "src\\core\\business_process\\optimizer\\refactored\\market_analyzer.py",
      "line_number": 19,
      "code_snippet": "class MarketAnalyzer:  # 388 lines",
      "suggested_fix": "将类拆分为多个职责单一的类",
      "risk_level": "high",
      "automated": false
    },
    {
      "opportunity_id": "long_params_create_config_-4909027964616350996",
      "title": "长参数列表: create_config",
      "description": "函数 create_config 参数过多 (8 个)，建议使用参数对象",
      "severity": "medium",
      "confidence": 0.8,
      "effort": "medium",
      "impact": "maintainability",
      "file_path": "src\\core\\business_process\\config\\config.py",
      "line_number": 57,
      "code_snippet": "def create_config(...):  # 8 parameters",
      "suggested_fix": "将相关参数封装为数据类或字典",
      "risk_level": "low",
      "automated": false
    },
    {
      "opportunity_id": "long_params_update_config_-4909027964616350996",
      "title": "长参数列表: update_config",
      "description": "函数 update_config 参数过多 (10 个)，建议使用参数对象",
      "severity": "medium",
      "confidence": 0.8,
      "effort": "medium",
      "impact": "maintainability",
      "file_path": "src\\core\\business_process\\config\\config.py",
      "line_number": 87,
      "code_snippet": "def update_config(...):  # 10 parameters",
      "suggested_fix": "将相关参数封装为数据类或字典",
      "risk_level": "low",
      "automated": false
    },
    {
      "opportunity_id": "long_params_list_configs_-4909027964616350996",
      "title": "长参数列表: list_configs",
      "description": "函数 list_configs 参数过多 (7 个)，建议使用参数对象",
      "severity": "medium",
      "confidence": 0.8,
      "effort": "medium",
      "impact": "maintainability",
      "file_path": "src\\core\\business_process\\config\\config.py",
      "line_number": 143,
      "code_snippet": "def list_configs(...):  # 7 parameters",
      "suggested_fix": "将相关参数封装为数据类或字典",
      "risk_level": "low",
      "automated": false
    },
    {
      "opportunity_id": "long_params_save_config_-4909027964616350996",
      "title": "长参数列表: save_config",
      "description": "函数 save_config 参数过多 (7 个)，建议使用参数对象",
      "severity": "medium",
      "confidence": 0.8,
      "effort": "medium",
      "impact": "maintainability",
      "file_path": "src\\core\\business_process\\config\\config.py",
      "line_number": 161,
      "code_snippet": "def save_config(...):  # 7 parameters",
      "suggested_fix": "将相关参数封装为数据类或字典",
      "risk_level": "low",
      "automated": false
    },
    {
      "opportunity_id": "long_params__serialize_config_-4909027964616350996",
      "title": "长参数列表: _serialize_config",
      "description": "函数 _serialize_config 参数过多 (20 个)，建议使用参数对象",
      "severity": "medium",
      "confidence": 0.8,
      "effort": "medium",
      "impact": "maintainability",
      "file_path": "src\\core\\business_process\\config\\config.py",
      "line_number": 176,
      "code_snippet": "def _serialize_config(...):  # 20 parameters",
      "suggested_fix": "将相关参数封装为数据类或字典",
      "risk_level": "low",
      "automated": false
    },
    {
      "opportunity_id": "long_params__deserialize_config_-4909027964616350996",
      "title": "长参数列表: _deserialize_config",
      "description": "函数 _deserialize_config 参数过多 (32 个)，建议使用参数对象",
      "severity": "medium",
      "confidence": 0.8,
      "effort": "medium",
      "impact": "maintainability",
      "file_path": "src\\core\\business_process\\config\\config.py",
      "line_number": 199,
      "code_snippet": "def _deserialize_config(...):  # 32 parameters",
      "suggested_fix": "将相关参数封装为数据类或字典",
      "risk_level": "low",
      "automated": false
    },
    {
      "opportunity_id": "long_params_compare_configs_-4909027964616350996",
      "title": "长参数列表: compare_configs",
      "description": "函数 compare_configs 参数过多 (7 个)，建议使用参数对象",
      "severity": "medium",
      "confidence": 0.8,
      "effort": "medium",
      "impact": "maintainability",
      "file_path": "src\\core\\business_process\\config\\config.py",
      "line_number": 298,
      "code_snippet": "def compare_configs(...):  # 7 parameters",
      "suggested_fix": "将相关参数封装为数据类或字典",
      "risk_level": "low",
      "automated": false
    },
    {
      "opportunity_id": "long_params_create_demo_config_-2439929738509655107",
      "title": "长参数列表: create_demo_config",
      "description": "函数 create_demo_config 参数过多 (7 个)，建议使用参数对象",
      "severity": "medium",
      "confidence": 0.8,
      "effort": "medium",
      "impact": "maintainability",
      "file_path": "src\\core\\business_process\\examples\\demo.py",
      "line_number": 769,
      "code_snippet": "def create_demo_config(...):  # 7 parameters",
      "suggested_fix": "将相关参数封装为数据类或字典",
      "risk_level": "low",
      "automated": false
    },
    {
      "opportunity_id": "long_params_reset_-2439929738509655107",
      "title": "长参数列表: reset",
      "description": "函数 reset 参数过多 (6 个)，建议使用参数对象",
      "severity": "medium",
      "confidence": 0.8,
      "effort": "medium",
      "impact": "maintainability",
      "file_path": "src\\core\\business_process\\examples\\demo.py",
      "line_number": 106,
      "code_snippet": "def reset(...):  # 6 parameters",
      "suggested_fix": "将相关参数封装为数据类或字典",
      "risk_level": "low",
      "automated": false
    },
    {
      "opportunity_id": "long_params_setup_process_event_handlers_-2439929738509655107",
      "title": "长参数列表: setup_process_event_handlers",
      "description": "函数 setup_process_event_handlers 参数过多 (8 个)，建议使用参数对象",
      "severity": "medium",
      "confidence": 0.8,
      "effort": "medium",
      "impact": "maintainability",
      "file_path": "src\\core\\business_process\\examples\\demo.py",
      "line_number": 205,
      "code_snippet": "def setup_process_event_handlers(...):  # 8 parameters",
      "suggested_fix": "将相关参数封装为数据类或字典",
      "risk_level": "low",
      "automated": false
    },
    {
      "opportunity_id": "long_params_get_components_-2439929738509655107",
      "title": "长参数列表: get_components",
      "description": "函数 get_components 参数过多 (6 个)，建议使用参数对象",
      "severity": "medium",
      "confidence": 0.8,
      "effort": "medium",
      "impact": "maintainability",
      "file_path": "src\\core\\business_process\\examples\\demo.py",
      "line_number": 403,
      "code_snippet": "def get_components(...):  # 6 parameters",
      "suggested_fix": "将相关参数封装为数据类或字典",
      "risk_level": "low",
      "automated": false
    },
    {
      "opportunity_id": "long_params_get_demo_status_-2439929738509655107",
      "title": "长参数列表: get_demo_status",
      "description": "函数 get_demo_status 参数过多 (11 个)，建议使用参数对象",
      "severity": "medium",
      "confidence": 0.8,
      "effort": "medium",
      "impact": "maintainability",
      "file_path": "src\\core\\business_process\\examples\\demo.py",
      "line_number": 423,
      "code_snippet": "def get_demo_status(...):  # 11 parameters",
      "suggested_fix": "将相关参数封装为数据类或字典",
      "risk_level": "low",
      "automated": false
    },
    {
      "opportunity_id": "long_params_setup_event_handlers_-2439929738509655107",
      "title": "长参数列表: setup_event_handlers",
      "description": "函数 setup_event_handlers 参数过多 (11 个)，建议使用参数对象",
      "severity": "medium",
      "confidence": 0.8,
      "effort": "medium",
      "impact": "maintainability",
      "file_path": "src\\core\\business_process\\examples\\demo.py",
      "line_number": 475,
      "code_snippet": "def setup_event_handlers(...):  # 11 parameters",
      "suggested_fix": "将相关参数封装为数据类或字典",
      "risk_level": "low",
      "automated": false
    },
    {
      "opportunity_id": "long_params__start_trading_cycle_-2439929738509655107",
      "title": "长参数列表: _start_trading_cycle",
      "description": "函数 _start_trading_cycle 参数过多 (8 个)，建议使用参数对象",
      "severity": "medium",
      "confidence": 0.8,
      "effort": "medium",
      "impact": "maintainability",
      "file_path": "src\\core\\business_process\\examples\\demo.py",
      "line_number": 654,
      "code_snippet": "def _start_trading_cycle(...):  # 8 parameters",
      "suggested_fix": "将相关参数封装为数据类或字典",
      "risk_level": "low",
      "automated": false
    },
    {
      "opportunity_id": "long_params_initialize_-2439929738509655107",
      "title": "长参数列表: initialize",
      "description": "函数 initialize 参数过多 (8 个)，建议使用参数对象",
      "severity": "medium",
      "confidence": 0.8,
      "effort": "medium",
      "impact": "maintainability",
      "file_path": "src\\core\\business_process\\examples\\demo.py",
      "line_number": 703,
      "code_snippet": "def initialize(...):  # 8 parameters",
      "suggested_fix": "将相关参数封装为数据类或字典",
      "risk_level": "low",
      "automated": false
    },
    {
      "opportunity_id": "long_params_integrate_process_-6232321750356635780",
      "title": "长参数列表: integrate_process",
      "description": "函数 integrate_process 参数过多 (6 个)，建议使用参数对象",
      "severity": "medium",
      "confidence": 0.8,
      "effort": "medium",
      "impact": "maintainability",
      "file_path": "src\\core\\business_process\\integration\\integration.py",
      "line_number": 215,
      "code_snippet": "def integrate_process(...):  # 6 parameters",
      "suggested_fix": "将相关参数封装为数据类或字典",
      "risk_level": "low",
      "automated": false
    },
    {
      "opportunity_id": "long_params__handle_data_collection_-6232321750356635780",
      "title": "长参数列表: _handle_data_collection",
      "description": "函数 _handle_data_collection 参数过多 (6 个)，建议使用参数对象",
      "severity": "medium",
      "confidence": 0.8,
      "effort": "medium",
      "impact": "maintainability",
      "file_path": "src\\core\\business_process\\integration\\integration.py",
      "line_number": 242,
      "code_snippet": "def _handle_data_collection(...):  # 6 parameters",
      "suggested_fix": "将相关参数封装为数据类或字典",
      "risk_level": "low",
      "automated": false
    },
    {
      "opportunity_id": "long_params__handle_feature_extraction_-6232321750356635780",
      "title": "长参数列表: _handle_feature_extraction",
      "description": "函数 _handle_feature_extraction 参数过多 (6 个)，建议使用参数对象",
      "severity": "medium",
      "confidence": 0.8,
      "effort": "medium",
      "impact": "maintainability",
      "file_path": "src\\core\\business_process\\integration\\integration.py",
      "line_number": 260,
      "code_snippet": "def _handle_feature_extraction(...):  # 6 parameters",
      "suggested_fix": "将相关参数封装为数据类或字典",
      "risk_level": "low",
      "automated": false
    },
    {
      "opportunity_id": "long_params__handle_model_prediction_-6232321750356635780",
      "title": "长参数列表: _handle_model_prediction",
      "description": "函数 _handle_model_prediction 参数过多 (6 个)，建议使用参数对象",
      "severity": "medium",
      "confidence": 0.8,
      "effort": "medium",
      "impact": "maintainability",
      "file_path": "src\\core\\business_process\\integration\\integration.py",
      "line_number": 278,
      "code_snippet": "def _handle_model_prediction(...):  # 6 parameters",
      "suggested_fix": "将相关参数封装为数据类或字典",
      "risk_level": "low",
      "automated": false
    },
    {
      "opportunity_id": "long_params__handle_strategy_decision_-6232321750356635780",
      "title": "长参数列表: _handle_strategy_decision",
      "description": "函数 _handle_strategy_decision 参数过多 (6 个)，建议使用参数对象",
      "severity": "medium",
      "confidence": 0.8,
      "effort": "medium",
      "impact": "maintainability",
      "file_path": "src\\core\\business_process\\integration\\integration.py",
      "line_number": 296,
      "code_snippet": "def _handle_strategy_decision(...):  # 6 parameters",
      "suggested_fix": "将相关参数封装为数据类或字典",
      "risk_level": "low",
      "automated": false
    },
    {
      "opportunity_id": "long_params__handle_risk_check_-6232321750356635780",
      "title": "长参数列表: _handle_risk_check",
      "description": "函数 _handle_risk_check 参数过多 (6 个)，建议使用参数对象",
      "severity": "medium",
      "confidence": 0.8,
      "effort": "medium",
      "impact": "maintainability",
      "file_path": "src\\core\\business_process\\integration\\integration.py",
      "line_number": 314,
      "code_snippet": "def _handle_risk_check(...):  # 6 parameters",
      "suggested_fix": "将相关参数封装为数据类或字典",
      "risk_level": "low",
      "automated": false
    },
    {
      "opportunity_id": "long_params__handle_trading_execution_-6232321750356635780",
      "title": "长参数列表: _handle_trading_execution",
      "description": "函数 _handle_trading_execution 参数过多 (6 个)，建议使用参数对象",
      "severity": "medium",
      "confidence": 0.8,
      "effort": "medium",
      "impact": "maintainability",
      "file_path": "src\\core\\business_process\\integration\\integration.py",
      "line_number": 332,
      "code_snippet": "def _handle_trading_execution(...):  # 6 parameters",
      "suggested_fix": "将相关参数封装为数据类或字典",
      "risk_level": "low",
      "automated": false
    },
    {
      "opportunity_id": "long_params__handle_monitoring_feedback_-6232321750356635780",
      "title": "长参数列表: _handle_monitoring_feedback",
      "description": "函数 _handle_monitoring_feedback 参数过多 (6 个)，建议使用参数对象",
      "severity": "medium",
      "confidence": 0.8,
      "effort": "medium",
      "impact": "maintainability",
      "file_path": "src\\core\\business_process\\integration\\integration.py",
      "line_number": 350,
      "code_snippet": "def _handle_monitoring_feedback(...):  # 6 parameters",
      "suggested_fix": "将相关参数封装为数据类或字典",
      "risk_level": "low",
      "automated": false
    },
    {
      "opportunity_id": "long_params__load_integration_configs_-6232321750356635780",
      "title": "长参数列表: _load_integration_configs",
      "description": "函数 _load_integration_configs 参数过多 (21 个)，建议使用参数对象",
      "severity": "medium",
      "confidence": 0.8,
      "effort": "medium",
      "impact": "maintainability",
      "file_path": "src\\core\\business_process\\integration\\integration.py",
      "line_number": 479,
      "code_snippet": "def _load_integration_configs(...):  # 21 parameters",
      "suggested_fix": "将相关参数封装为数据类或字典",
      "risk_level": "low",
      "automated": false
    },
    {
      "opportunity_id": "long_params_start_trading_cycle_-6232321750356635780",
      "title": "长参数列表: start_trading_cycle",
      "description": "函数 start_trading_cycle 参数过多 (6 个)，建议使用参数对象",
      "severity": "medium",
      "confidence": 0.8,
      "effort": "medium",
      "impact": "maintainability",
      "file_path": "src\\core\\business_process\\integration\\integration.py",
      "line_number": 589,
      "code_snippet": "def start_trading_cycle(...):  # 6 parameters",
      "suggested_fix": "将相关参数封装为数据类或字典",
      "risk_level": "low",
      "automated": false
    },
    {
      "opportunity_id": "long_params_add_error_-931910376757206320",
      "title": "长参数列表: add_error",
      "description": "函数 add_error 参数过多 (8 个)，建议使用参数对象",
      "severity": "medium",
      "confidence": 0.8,
      "effort": "medium",
      "impact": "maintainability",
      "file_path": "src\\core\\business_process\\models\\models.py",
      "line_number": 105,
      "code_snippet": "def add_error(...):  # 8 parameters",
      "suggested_fix": "将相关参数封装为数据类或字典",
      "risk_level": "low",
      "automated": false
    },
    {
      "opportunity_id": "long_params_register_process_-9053448142391411505",
      "title": "长参数列表: register_process",
      "description": "函数 register_process 参数过多 (7 个)，建议使用参数对象",
      "severity": "medium",
      "confidence": 0.8,
      "effort": "medium",
      "impact": "maintainability",
      "file_path": "src\\core\\business_process\\monitor\\monitor.py",
      "line_number": 28,
      "code_snippet": "def register_process(...):  # 7 parameters",
      "suggested_fix": "将相关参数封装为数据类或字典",
      "risk_level": "low",
      "automated": false
    },
    {
      "opportunity_id": "long_params_add_alert_-9053448142391411505",
      "title": "长参数列表: add_alert",
      "description": "函数 add_alert 参数过多 (7 个)，建议使用参数对象",
      "severity": "medium",
      "confidence": 0.8,
      "effort": "medium",
      "impact": "maintainability",
      "file_path": "src\\core\\business_process\\monitor\\monitor.py",
      "line_number": 63,
      "code_snippet": "def add_alert(...):  # 7 parameters",
      "suggested_fix": "将相关参数封装为数据类或字典",
      "risk_level": "low",
      "automated": false
    },
    {
      "opportunity_id": "long_params___init___-9053448142391411505",
      "title": "长参数列表: __init__",
      "description": "函数 __init__ 参数过多 (8 个)，建议使用参数对象",
      "severity": "medium",
      "confidence": 0.8,
      "effort": "medium",
      "impact": "maintainability",
      "file_path": "src\\core\\business_process\\monitor\\monitor.py",
      "line_number": 82,
      "code_snippet": "def __init__(...):  # 8 parameters",
      "suggested_fix": "将相关参数封装为数据类或字典",
      "risk_level": "low",
      "automated": false
    },
    {
      "opportunity_id": "long_params__monitor_single_process_-9053448142391411505",
      "title": "长参数列表: _monitor_single_process",
      "description": "函数 _monitor_single_process 参数过多 (10 个)，建议使用参数对象",
      "severity": "medium",
      "confidence": 0.8,
      "effort": "medium",
      "impact": "maintainability",
      "file_path": "src\\core\\business_process\\monitor\\monitor.py",
      "line_number": 159,
      "code_snippet": "def _monitor_single_process(...):  # 10 parameters",
      "suggested_fix": "将相关参数封装为数据类或字典",
      "risk_level": "low",
      "automated": false
    },
    {
      "opportunity_id": "long_params__collect_system_metrics_-9053448142391411505",
      "title": "长参数列表: _collect_system_metrics",
      "description": "函数 _collect_system_metrics 参数过多 (6 个)，建议使用参数对象",
      "severity": "medium",
      "confidence": 0.8,
      "effort": "medium",
      "impact": "maintainability",
      "file_path": "src\\core\\business_process\\monitor\\monitor.py",
      "line_number": 186,
      "code_snippet": "def _collect_system_metrics(...):  # 6 parameters",
      "suggested_fix": "将相关参数封装为数据类或字典",
      "risk_level": "low",
      "automated": false
    },
    {
      "opportunity_id": "long_params__collect_process_metrics_-9053448142391411505",
      "title": "长参数列表: _collect_process_metrics",
      "description": "函数 _collect_process_metrics 参数过多 (12 个)，建议使用参数对象",
      "severity": "medium",
      "confidence": 0.8,
      "effort": "medium",
      "impact": "maintainability",
      "file_path": "src\\core\\business_process\\monitor\\monitor.py",
      "line_number": 200,
      "code_snippet": "def _collect_process_metrics(...):  # 12 parameters",
      "suggested_fix": "将相关参数封装为数据类或字典",
      "risk_level": "low",
      "automated": false
    },
    {
      "opportunity_id": "long_params__estimate_progress_ratio_-9053448142391411505",
      "title": "长参数列表: _estimate_progress_ratio",
      "description": "函数 _estimate_progress_ratio 参数过多 (18 个)，建议使用参数对象",
      "severity": "medium",
      "confidence": 0.8,
      "effort": "medium",
      "impact": "maintainability",
      "file_path": "src\\core\\business_process\\monitor\\monitor.py",
      "line_number": 225,
      "code_snippet": "def _estimate_progress_ratio(...):  # 18 parameters",
      "suggested_fix": "将相关参数封装为数据类或字典",
      "risk_level": "low",
      "automated": false
    },
    {
      "opportunity_id": "long_params__check_performance_thresholds_-9053448142391411505",
      "title": "长参数列表: _check_performance_thresholds",
      "description": "函数 _check_performance_thresholds 参数过多 (7 个)，建议使用参数对象",
      "severity": "medium",
      "confidence": 0.8,
      "effort": "medium",
      "impact": "maintainability",
      "file_path": "src\\core\\business_process\\monitor\\monitor.py",
      "line_number": 258,
      "code_snippet": "def _check_performance_thresholds(...):  # 7 parameters",
      "suggested_fix": "将相关参数封装为数据类或字典",
      "risk_level": "low",
      "automated": false
    },
    {
      "opportunity_id": "long_params__trigger_timeout_alert_-9053448142391411505",
      "title": "长参数列表: _trigger_timeout_alert",
      "description": "函数 _trigger_timeout_alert 参数过多 (10 个)，建议使用参数对象",
      "severity": "medium",
      "confidence": 0.8,
      "effort": "medium",
      "impact": "maintainability",
      "file_path": "src\\core\\business_process\\monitor\\monitor.py",
      "line_number": 273,
      "code_snippet": "def _trigger_timeout_alert(...):  # 10 parameters",
      "suggested_fix": "将相关参数封装为数据类或字典",
      "risk_level": "low",
      "automated": false
    },
    {
      "opportunity_id": "long_params__trigger_performance_alert_-9053448142391411505",
      "title": "长参数列表: _trigger_performance_alert",
      "description": "函数 _trigger_performance_alert 参数过多 (8 个)，建议使用参数对象",
      "severity": "medium",
      "confidence": 0.8,
      "effort": "medium",
      "impact": "maintainability",
      "file_path": "src\\core\\business_process\\monitor\\monitor.py",
      "line_number": 289,
      "code_snippet": "def _trigger_performance_alert(...):  # 8 parameters",
      "suggested_fix": "将相关参数封装为数据类或字典",
      "risk_level": "low",
      "automated": false
    },
    {
      "opportunity_id": "long_params__trigger_error_rate_alert_-9053448142391411505",
      "title": "长参数列表: _trigger_error_rate_alert",
      "description": "函数 _trigger_error_rate_alert 参数过多 (7 个)，建议使用参数对象",
      "severity": "medium",
      "confidence": 0.8,
      "effort": "medium",
      "impact": "maintainability",
      "file_path": "src\\core\\business_process\\monitor\\monitor.py",
      "line_number": 301,
      "code_snippet": "def _trigger_error_rate_alert(...):  # 7 parameters",
      "suggested_fix": "将相关参数封装为数据类或字典",
      "risk_level": "low",
      "automated": false
    },
    {
      "opportunity_id": "long_params_create_process_context_2538342419693368025",
      "title": "长参数列表: create_process_context",
      "description": "函数 create_process_context 参数过多 (8 个)，建议使用参数对象",
      "severity": "medium",
      "confidence": 0.8,
      "effort": "medium",
      "impact": "maintainability",
      "file_path": "src\\core\\business_process\\optimizer\\models.py",
      "line_number": 208,
      "code_snippet": "def create_process_context(...):  # 8 parameters",
      "suggested_fix": "将相关参数封装为数据类或字典",
      "risk_level": "low",
      "automated": false
    },
    {
      "opportunity_id": "long_params_to_dict_2538342419693368025",
      "title": "长参数列表: to_dict",
      "description": "函数 to_dict 参数过多 (12 个)，建议使用参数对象",
      "severity": "medium",
      "confidence": 0.8,
      "effort": "medium",
      "impact": "maintainability",
      "file_path": "src\\core\\business_process\\optimizer\\models.py",
      "line_number": 74,
      "code_snippet": "def to_dict(...):  # 12 parameters",
      "suggested_fix": "将相关参数封装为数据类或字典",
      "risk_level": "low",
      "automated": false
    },
    {
      "opportunity_id": "long_params_to_dict_2538342419693368025",
      "title": "长参数列表: to_dict",
      "description": "函数 to_dict 参数过多 (13 个)，建议使用参数对象",
      "severity": "medium",
      "confidence": 0.8,
      "effort": "medium",
      "impact": "maintainability",
      "file_path": "src\\core\\business_process\\optimizer\\models.py",
      "line_number": 110,
      "code_snippet": "def to_dict(...):  # 13 parameters",
      "suggested_fix": "将相关参数封装为数据类或字典",
      "risk_level": "low",
      "automated": false
    },
    {
      "opportunity_id": "long_params_to_dict_2538342419693368025",
      "title": "长参数列表: to_dict",
      "description": "函数 to_dict 参数过多 (10 个)，建议使用参数对象",
      "severity": "medium",
      "confidence": 0.8,
      "effort": "medium",
      "impact": "maintainability",
      "file_path": "src\\core\\business_process\\optimizer\\models.py",
      "line_number": 157,
      "code_snippet": "def to_dict(...):  # 10 parameters",
      "suggested_fix": "将相关参数封装为数据类或字典",
      "risk_level": "low",
      "automated": false
    },
    {
      "opportunity_id": "long_params_to_dict_2538342419693368025",
      "title": "长参数列表: to_dict",
      "description": "函数 to_dict 参数过多 (11 个)，建议使用参数对象",
      "severity": "medium",
      "confidence": 0.8,
      "effort": "medium",
      "impact": "maintainability",
      "file_path": "src\\core\\business_process\\optimizer\\models.py",
      "line_number": 190,
      "code_snippet": "def to_dict(...):  # 11 parameters",
      "suggested_fix": "将相关参数封装为数据类或字典",
      "risk_level": "low",
      "automated": false
    },
    {
      "opportunity_id": "long_params___init___5247489382654986553",
      "title": "长参数列表: __init__",
      "description": "函数 __init__ 参数过多 (10 个)，建议使用参数对象",
      "severity": "medium",
      "confidence": 0.8,
      "effort": "medium",
      "impact": "maintainability",
      "file_path": "src\\core\\business_process\\optimizer\\optimizer_refactored.py",
      "line_number": 85,
      "code_snippet": "def __init__(...):  # 10 parameters",
      "suggested_fix": "将相关参数封装为数据类或字典",
      "risk_level": "low",
      "automated": false
    },
    {
      "opportunity_id": "long_params_get_optimization_status_5247489382654986553",
      "title": "长参数列表: get_optimization_status",
      "description": "函数 get_optimization_status 参数过多 (15 个)，建议使用参数对象",
      "severity": "medium",
      "confidence": 0.8,
      "effort": "medium",
      "impact": "maintainability",
      "file_path": "src\\core\\business_process\\optimizer\\optimizer_refactored.py",
      "line_number": 260,
      "code_snippet": "def get_optimization_status(...):  # 15 parameters",
      "suggested_fix": "将相关参数封装为数据类或字典",
      "risk_level": "low",
      "automated": false
    },
    {
      "opportunity_id": "long_params__convert_legacy_config_5247489382654986553",
      "title": "长参数列表: _convert_legacy_config",
      "description": "函数 _convert_legacy_config 参数过多 (14 个)，建议使用参数对象",
      "severity": "medium",
      "confidence": 0.8,
      "effort": "medium",
      "impact": "maintainability",
      "file_path": "src\\core\\business_process\\optimizer\\optimizer_refactored.py",
      "line_number": 297,
      "code_snippet": "def _convert_legacy_config(...):  # 14 parameters",
      "suggested_fix": "将相关参数封装为数据类或字典",
      "risk_level": "low",
      "automated": false
    },
    {
      "opportunity_id": "long_params__build_legacy_result_5247489382654986553",
      "title": "长参数列表: _build_legacy_result",
      "description": "函数 _build_legacy_result 参数过多 (17 个)，建议使用参数对象",
      "severity": "medium",
      "confidence": 0.8,
      "effort": "medium",
      "impact": "maintainability",
      "file_path": "src\\core\\business_process\\optimizer\\optimizer_refactored.py",
      "line_number": 318,
      "code_snippet": "def _build_legacy_result(...):  # 17 parameters",
      "suggested_fix": "将相关参数封装为数据类或字典",
      "risk_level": "low",
      "automated": false
    },
    {
      "opportunity_id": "long_params___init___6351461332442769695",
      "title": "长参数列表: __init__",
      "description": "函数 __init__ 参数过多 (6 个)，建议使用参数对象",
      "severity": "medium",
      "confidence": 0.8,
      "effort": "medium",
      "impact": "maintainability",
      "file_path": "src\\core\\business_process\\optimizer\\components\\decision_engine.py",
      "line_number": 42,
      "code_snippet": "def __init__(...):  # 6 parameters",
      "suggested_fix": "将相关参数封装为数据类或字典",
      "risk_level": "low",
      "automated": false
    },
    {
      "opportunity_id": "long_params_get_status_6351461332442769695",
      "title": "长参数列表: get_status",
      "description": "函数 get_status 参数过多 (7 个)，建议使用参数对象",
      "severity": "medium",
      "confidence": 0.8,
      "effort": "medium",
      "impact": "maintainability",
      "file_path": "src\\core\\business_process\\optimizer\\components\\decision_engine.py",
      "line_number": 201,
      "code_snippet": "def get_status(...):  # 7 parameters",
      "suggested_fix": "将相关参数封装为数据类或字典",
      "risk_level": "low",
      "automated": false
    },
    {
      "opportunity_id": "long_params__make_conservative_decision_6351461332442769695",
      "title": "长参数列表: _make_conservative_decision",
      "description": "函数 _make_conservative_decision 参数过多 (6 个)，建议使用参数对象",
      "severity": "medium",
      "confidence": 0.8,
      "effort": "medium",
      "impact": "maintainability",
      "file_path": "src\\core\\business_process\\optimizer\\components\\decision_engine.py",
      "line_number": 227,
      "code_snippet": "def _make_conservative_decision(...):  # 6 parameters",
      "suggested_fix": "将相关参数封装为数据类或字典",
      "risk_level": "low",
      "automated": false
    },
    {
      "opportunity_id": "long_params__make_aggressive_decision_6351461332442769695",
      "title": "长参数列表: _make_aggressive_decision",
      "description": "函数 _make_aggressive_decision 参数过多 (7 个)，建议使用参数对象",
      "severity": "medium",
      "confidence": 0.8,
      "effort": "medium",
      "impact": "maintainability",
      "file_path": "src\\core\\business_process\\optimizer\\components\\decision_engine.py",
      "line_number": 243,
      "code_snippet": "def _make_aggressive_decision(...):  # 7 parameters",
      "suggested_fix": "将相关参数封装为数据类或字典",
      "risk_level": "low",
      "automated": false
    },
    {
      "opportunity_id": "long_params__make_balanced_decision_6351461332442769695",
      "title": "长参数列表: _make_balanced_decision",
      "description": "函数 _make_balanced_decision 参数过多 (6 个)，建议使用参数对象",
      "severity": "medium",
      "confidence": 0.8,
      "effort": "medium",
      "impact": "maintainability",
      "file_path": "src\\core\\business_process\\optimizer\\components\\decision_engine.py",
      "line_number": 259,
      "code_snippet": "def _make_balanced_decision(...):  # 6 parameters",
      "suggested_fix": "将相关参数封装为数据类或字典",
      "risk_level": "low",
      "automated": false
    },
    {
      "opportunity_id": "long_params_get_status_3135289770125234907",
      "title": "长参数列表: get_status",
      "description": "函数 get_status 参数过多 (7 个)，建议使用参数对象",
      "severity": "medium",
      "confidence": 0.8,
      "effort": "medium",
      "impact": "maintainability",
      "file_path": "src\\core\\business_process\\optimizer\\components\\performance_analyzer.py",
      "line_number": 155,
      "code_snippet": "def get_status(...):  # 7 parameters",
      "suggested_fix": "将相关参数封装为数据类或字典",
      "risk_level": "low",
      "automated": false
    },
    {
      "opportunity_id": "long_params__extract_market_metrics_3135289770125234907",
      "title": "长参数列表: _extract_market_metrics",
      "description": "函数 _extract_market_metrics 参数过多 (8 个)，建议使用参数对象",
      "severity": "medium",
      "confidence": 0.8,
      "effort": "medium",
      "impact": "maintainability",
      "file_path": "src\\core\\business_process\\optimizer\\components\\performance_analyzer.py",
      "line_number": 169,
      "code_snippet": "def _extract_market_metrics(...):  # 8 parameters",
      "suggested_fix": "将相关参数封装为数据类或字典",
      "risk_level": "low",
      "automated": false
    },
    {
      "opportunity_id": "long_params__calculate_market_score_3135289770125234907",
      "title": "长参数列表: _calculate_market_score",
      "description": "函数 _calculate_market_score 参数过多 (8 个)，建议使用参数对象",
      "severity": "medium",
      "confidence": 0.8,
      "effort": "medium",
      "impact": "maintainability",
      "file_path": "src\\core\\business_process\\optimizer\\components\\performance_analyzer.py",
      "line_number": 196,
      "code_snippet": "def _calculate_market_score(...):  # 8 parameters",
      "suggested_fix": "将相关参数封装为数据类或字典",
      "risk_level": "low",
      "automated": false
    },
    {
      "opportunity_id": "long_params__generate_market_recommendations_3135289770125234907",
      "title": "长参数列表: _generate_market_recommendations",
      "description": "函数 _generate_market_recommendations 参数过多 (6 个)，建议使用参数对象",
      "severity": "medium",
      "confidence": 0.8,
      "effort": "medium",
      "impact": "maintainability",
      "file_path": "src\\core\\business_process\\optimizer\\components\\performance_analyzer.py",
      "line_number": 205,
      "code_snippet": "def _generate_market_recommendations(...):  # 6 parameters",
      "suggested_fix": "将相关参数封装为数据类或字典",
      "risk_level": "low",
      "automated": false
    },
    {
      "opportunity_id": "long_params__collect_process_metrics_3135289770125234907",
      "title": "长参数列表: _collect_process_metrics",
      "description": "函数 _collect_process_metrics 参数过多 (7 个)，建议使用参数对象",
      "severity": "medium",
      "confidence": 0.8,
      "effort": "medium",
      "impact": "maintainability",
      "file_path": "src\\core\\business_process\\optimizer\\components\\performance_analyzer.py",
      "line_number": 219,
      "code_snippet": "def _collect_process_metrics(...):  # 7 parameters",
      "suggested_fix": "将相关参数封装为数据类或字典",
      "risk_level": "low",
      "automated": false
    },
    {
      "opportunity_id": "long_params_get_status_-2724420683521343566",
      "title": "长参数列表: get_status",
      "description": "函数 get_status 参数过多 (9 个)，建议使用参数对象",
      "severity": "medium",
      "confidence": 0.8,
      "effort": "medium",
      "impact": "maintainability",
      "file_path": "src\\core\\business_process\\optimizer\\components\\process_executor.py",
      "line_number": 196,
      "code_snippet": "def get_status(...):  # 9 parameters",
      "suggested_fix": "将相关参数封装为数据类或字典",
      "risk_level": "low",
      "automated": false
    },
    {
      "opportunity_id": "long_params_get_monitoring_report_1154821944592946160",
      "title": "长参数列表: get_monitoring_report",
      "description": "函数 get_monitoring_report 参数过多 (12 个)，建议使用参数对象",
      "severity": "medium",
      "confidence": 0.8,
      "effort": "medium",
      "impact": "maintainability",
      "file_path": "src\\core\\business_process\\optimizer\\components\\process_monitor.py",
      "line_number": 208,
      "code_snippet": "def get_monitoring_report(...):  # 12 parameters",
      "suggested_fix": "将相关参数封装为数据类或字典",
      "risk_level": "low",
      "automated": false
    },
    {
      "opportunity_id": "long_params_get_status_1154821944592946160",
      "title": "长参数列表: get_status",
      "description": "函数 get_status 参数过多 (6 个)，建议使用参数对象",
      "severity": "medium",
      "confidence": 0.8,
      "effort": "medium",
      "impact": "maintainability",
      "file_path": "src\\core\\business_process\\optimizer\\components\\process_monitor.py",
      "line_number": 247,
      "code_snippet": "def get_status(...):  # 6 parameters",
      "suggested_fix": "将相关参数封装为数据类或字典",
      "risk_level": "low",
      "automated": false
    },
    {
      "opportunity_id": "long_params__get_recent_alerts_1154821944592946160",
      "title": "长参数列表: _get_recent_alerts",
      "description": "函数 _get_recent_alerts 参数过多 (8 个)，建议使用参数对象",
      "severity": "medium",
      "confidence": 0.8,
      "effort": "medium",
      "impact": "maintainability",
      "file_path": "src\\core\\business_process\\optimizer\\components\\process_monitor.py",
      "line_number": 332,
      "code_snippet": "def _get_recent_alerts(...):  # 8 parameters",
      "suggested_fix": "将相关参数封装为数据类或字典",
      "risk_level": "low",
      "automated": false
    },
    {
      "opportunity_id": "long_params_prioritize_recommendations_-5947762189228750654",
      "title": "长参数列表: prioritize_recommendations",
      "description": "函数 prioritize_recommendations 参数过多 (8 个)，建议使用参数对象",
      "severity": "medium",
      "confidence": 0.8,
      "effort": "medium",
      "impact": "maintainability",
      "file_path": "src\\core\\business_process\\optimizer\\components\\recommendation_generator.py",
      "line_number": 186,
      "code_snippet": "def prioritize_recommendations(...):  # 8 parameters",
      "suggested_fix": "将相关参数封装为数据类或字典",
      "risk_level": "low",
      "automated": false
    },
    {
      "opportunity_id": "long_params_track_implementation_-5947762189228750654",
      "title": "长参数列表: track_implementation",
      "description": "函数 track_implementation 参数过多 (6 个)，建议使用参数对象",
      "severity": "medium",
      "confidence": 0.8,
      "effort": "medium",
      "impact": "maintainability",
      "file_path": "src\\core\\business_process\\optimizer\\components\\recommendation_generator.py",
      "line_number": 211,
      "code_snippet": "def track_implementation(...):  # 6 parameters",
      "suggested_fix": "将相关参数封装为数据类或字典",
      "risk_level": "low",
      "automated": false
    },
    {
      "opportunity_id": "long_params_get_status_-5947762189228750654",
      "title": "长参数列表: get_status",
      "description": "函数 get_status 参数过多 (7 个)，建议使用参数对象",
      "severity": "medium",
      "confidence": 0.8,
      "effort": "medium",
      "impact": "maintainability",
      "file_path": "src\\core\\business_process\\optimizer\\components\\recommendation_generator.py",
      "line_number": 257,
      "code_snippet": "def get_status(...):  # 7 parameters",
      "suggested_fix": "将相关参数封装为数据类或字典",
      "risk_level": "low",
      "automated": false
    },
    {
      "opportunity_id": "long_params_to_dict_21956870279528526",
      "title": "长参数列表: to_dict",
      "description": "函数 to_dict 参数过多 (15 个)，建议使用参数对象",
      "severity": "medium",
      "confidence": 0.8,
      "effort": "medium",
      "impact": "maintainability",
      "file_path": "src\\core\\business_process\\optimizer\\configs\\optimizer_configs.py",
      "line_number": 205,
      "code_snippet": "def to_dict(...):  # 15 parameters",
      "suggested_fix": "将相关参数封装为数据类或字典",
      "risk_level": "low",
      "automated": false
    },
    {
      "opportunity_id": "long_params_from_dict_21956870279528526",
      "title": "长参数列表: from_dict",
      "description": "函数 from_dict 参数过多 (27 个)，建议使用参数对象",
      "severity": "medium",
      "confidence": 0.8,
      "effort": "medium",
      "impact": "maintainability",
      "file_path": "src\\core\\business_process\\optimizer\\configs\\optimizer_configs.py",
      "line_number": 226,
      "code_snippet": "def from_dict(...):  # 27 parameters",
      "suggested_fix": "将相关参数封装为数据类或字典",
      "risk_level": "low",
      "automated": false
    },
    {
      "opportunity_id": "long_params___init___192957834875483427",
      "title": "长参数列表: __init__",
      "description": "函数 __init__ 参数过多 (10 个)，建议使用参数对象",
      "severity": "medium",
      "confidence": 0.8,
      "effort": "medium",
      "impact": "maintainability",
      "file_path": "src\\core\\business_process\\optimizer\\refactored\\market_analyzer.py",
      "line_number": 36,
      "code_snippet": "def __init__(...):  # 10 parameters",
      "suggested_fix": "将相关参数封装为数据类或字典",
      "risk_level": "low",
      "automated": false
    },
    {
      "opportunity_id": "long_params__initialize_state_timeouts_1093534533340970633",
      "title": "长参数列表: _initialize_state_timeouts",
      "description": "函数 _initialize_state_timeouts 参数过多 (18 个)，建议使用参数对象",
      "severity": "medium",
      "confidence": 0.8,
      "effort": "medium",
      "impact": "maintainability",
      "file_path": "src\\core\\business_process\\state_machine\\state_machine.py",
      "line_number": 31,
      "code_snippet": "def _initialize_state_timeouts(...):  # 18 parameters",
      "suggested_fix": "将相关参数封装为数据类或字典",
      "risk_level": "low",
      "automated": false
    },
    {
      "opportunity_id": "long_params_transition_to_1093534533340970633",
      "title": "长参数列表: transition_to",
      "description": "函数 transition_to 参数过多 (16 个)，建议使用参数对象",
      "severity": "medium",
      "confidence": 0.8,
      "effort": "medium",
      "impact": "maintainability",
      "file_path": "src\\core\\business_process\\state_machine\\state_machine.py",
      "line_number": 95,
      "code_snippet": "def transition_to(...):  # 16 parameters",
      "suggested_fix": "将相关参数封装为数据类或字典",
      "risk_level": "low",
      "automated": false
    },
    {
      "opportunity_id": "long_params__is_valid_transition_1093534533340970633",
      "title": "长参数列表: _is_valid_transition",
      "description": "函数 _is_valid_transition 参数过多 (33 个)，建议使用参数对象",
      "severity": "medium",
      "confidence": 0.8,
      "effort": "medium",
      "impact": "maintainability",
      "file_path": "src\\core\\business_process\\state_machine\\state_machine.py",
      "line_number": 144,
      "code_snippet": "def _is_valid_transition(...):  # 33 parameters",
      "suggested_fix": "将相关参数封装为数据类或字典",
      "risk_level": "low",
      "automated": false
    },
    {
      "opportunity_id": "long_params__publish_state_change_event_1093534533340970633",
      "title": "长参数列表: _publish_state_change_event",
      "description": "函数 _publish_state_change_event 参数过多 (10 个)，建议使用参数对象",
      "severity": "medium",
      "confidence": 0.8,
      "effort": "medium",
      "impact": "maintainability",
      "file_path": "src\\core\\business_process\\state_machine\\state_machine.py",
      "line_number": 170,
      "code_snippet": "def _publish_state_change_event(...):  # 10 parameters",
      "suggested_fix": "将相关参数封装为数据类或字典",
      "risk_level": "low",
      "automated": false
    },
    {
      "opportunity_id": "unused_import_Enum_6351461332442769695",
      "title": "未使用导入: Enum",
      "description": "导入 Enum 在文件中未使用",
      "severity": "low",
      "confidence": 0.8,
      "effort": "low",
      "impact": "maintainability",
      "file_path": "src\\core\\business_process\\optimizer\\components\\decision_engine.py",
      "line_number": 1,
      "code_snippet": "import Enum",
      "suggested_fix": "删除未使用的导入",
      "risk_level": "low",
      "automated": true
    },
    {
      "opportunity_id": "deep_nesting_-4909027964616350996_46",
      "title": "深层嵌套重构",
      "description": "代码嵌套过深 (7 层)，影响可读性",
      "severity": "medium",
      "confidence": 0.75,
      "effort": "low",
      "impact": "maintainability",
      "file_path": "src\\core\\business_process\\config\\config.py",
      "line_number": 47,
      "code_snippet": "self._config_versions[config.process_id] = []",
      "suggested_fix": "提取嵌套代码为独立函数，或使用早期返回",
      "risk_level": "low",
      "automated": true
    },
    {
      "opportunity_id": "deep_nesting_-4909027964616350996_48",
      "title": "深层嵌套重构",
      "description": "代码嵌套过深 (7 层)，影响可读性",
      "severity": "medium",
      "confidence": 0.75,
      "effort": "low",
      "impact": "maintainability",
      "file_path": "src\\core\\business_process\\config\\config.py",
      "line_number": 49,
      "code_snippet": "self._config_versions[config.process_id].append(version_key)",
      "suggested_fix": "提取嵌套代码为独立函数，或使用早期返回",
      "risk_level": "low",
      "automated": true
    },
    {
      "opportunity_id": "deep_nesting_-2439929738509655107_458",
      "title": "深层嵌套重构",
      "description": "代码嵌套过深 (9 层)，影响可读性",
      "severity": "medium",
      "confidence": 0.75,
      "effort": "low",
      "impact": "maintainability",
      "file_path": "src\\core\\business_process\\examples\\demo.py",
      "line_number": 459,
      "code_snippet": "metrics['total_processes']) * 100",
      "suggested_fix": "提取嵌套代码为独立函数，或使用早期返回",
      "risk_level": "low",
      "automated": true
    },
    {
      "opportunity_id": "deep_nesting_-2439929738509655107_460",
      "title": "深层嵌套重构",
      "description": "代码嵌套过深 (9 层)，影响可读性",
      "severity": "medium",
      "confidence": 0.75,
      "effort": "low",
      "impact": "maintainability",
      "file_path": "src\\core\\business_process\\examples\\demo.py",
      "line_number": 461,
      "code_snippet": "metrics['total_processes']) * 100",
      "suggested_fix": "提取嵌套代码为独立函数，或使用早期返回",
      "risk_level": "low",
      "automated": true
    },
    {
      "opportunity_id": "deep_nesting_-6232321750356635780_534",
      "title": "深层嵌套重构",
      "description": "代码嵌套过深 (7 层)，影响可读性",
      "severity": "medium",
      "confidence": 0.75,
      "effort": "low",
      "impact": "maintainability",
      "file_path": "src\\core\\business_process\\integration\\integration.py",
      "line_number": 535,
      "code_snippet": "logger.warning(f\"架构层 {layer_name} 健康状态异常\")",
      "suggested_fix": "提取嵌套代码为独立函数，或使用早期返回",
      "risk_level": "low",
      "automated": true
    },
    {
      "opportunity_id": "deep_nesting_-9053448142391411505_159",
      "title": "深层嵌套重构",
      "description": "代码嵌套过深 (8 层)，影响可读性",
      "severity": "medium",
      "confidence": 0.75,
      "effort": "low",
      "impact": "maintainability",
      "file_path": "src\\core\\business_process\\monitor\\monitor.py",
      "line_number": 160,
      "code_snippet": "system_metrics: Dict[str, Any]) -> None:",
      "suggested_fix": "提取嵌套代码为独立函数，或使用早期返回",
      "risk_level": "low",
      "automated": true
    },
    {
      "opportunity_id": "deep_nesting_-9053448142391411505_200",
      "title": "深层嵌套重构",
      "description": "代码嵌套过深 (8 层)，影响可读性",
      "severity": "medium",
      "confidence": 0.75,
      "effort": "low",
      "impact": "maintainability",
      "file_path": "src\\core\\business_process\\monitor\\monitor.py",
      "line_number": 201,
      "code_snippet": "system_metrics: Dict[str, Any]) -> Dict[str, Any]:",
      "suggested_fix": "提取嵌套代码为独立函数，或使用早期返回",
      "risk_level": "low",
      "automated": true
    },
    {
      "opportunity_id": "deep_nesting_2538342419693368025_208",
      "title": "深层嵌套重构",
      "description": "代码嵌套过深 (6 层)，影响可读性",
      "severity": "medium",
      "confidence": 0.75,
      "effort": "low",
      "impact": "maintainability",
      "file_path": "src\\core\\business_process\\optimizer\\models.py",
      "line_number": 209,
      "code_snippet": "market_data: Dict[str, Any],",
      "suggested_fix": "提取嵌套代码为独立函数，或使用早期返回",
      "risk_level": "low",
      "automated": true
    },
    {
      "opportunity_id": "deep_nesting_2538342419693368025_209",
      "title": "深层嵌套重构",
      "description": "代码嵌套过深 (6 层)，影响可读性",
      "severity": "medium",
      "confidence": 0.75,
      "effort": "low",
      "impact": "maintainability",
      "file_path": "src\\core\\business_process\\optimizer\\models.py",
      "line_number": 210,
      "code_snippet": "**kwargs) -> ProcessContext:",
      "suggested_fix": "提取嵌套代码为独立函数，或使用早期返回",
      "risk_level": "low",
      "automated": true
    },
    {
      "opportunity_id": "deep_nesting_2538342419693368025_231",
      "title": "深层嵌套重构",
      "description": "代码嵌套过深 (7 层)，影响可读性",
      "severity": "medium",
      "confidence": 0.75,
      "effort": "low",
      "impact": "maintainability",
      "file_path": "src\\core\\business_process\\optimizer\\models.py",
      "line_number": 232,
      "code_snippet": "status: OptimizationStatus = OptimizationStatus.PENDING) -> OptimizationResult:",
      "suggested_fix": "提取嵌套代码为独立函数，或使用早期返回",
      "risk_level": "low",
      "automated": true
    },
    {
      "opportunity_id": "deep_nesting_5247489382654986553_165",
      "title": "深层嵌套重构",
      "description": "代码嵌套过深 (9 层)，影响可读性",
      "severity": "medium",
      "confidence": 0.75,
      "effort": "low",
      "impact": "maintainability",
      "file_path": "src\\core\\business_process\\optimizer\\optimizer_refactored.py",
      "line_number": 166,
      "code_snippet": "risk_profile: Dict[str, Any]) -> Dict[str, Any]:",
      "suggested_fix": "提取嵌套代码为独立函数，或使用早期返回",
      "risk_level": "low",
      "automated": true
    },
    {
      "opportunity_id": "deep_nesting_6351461332442769695_69",
      "title": "深层嵌套重构",
      "description": "代码嵌套过深 (8 层)，影响可读性",
      "severity": "medium",
      "confidence": 0.75,
      "effort": "low",
      "impact": "maintainability",
      "file_path": "src\\core\\business_process\\optimizer\\components\\decision_engine.py",
      "line_number": 70,
      "code_snippet": "analysis: Any) -> DecisionResult:",
      "suggested_fix": "提取嵌套代码为独立函数，或使用早期返回",
      "risk_level": "low",
      "automated": true
    },
    {
      "opportunity_id": "deep_nesting_6351461332442769695_278",
      "title": "深层嵌套重构",
      "description": "代码嵌套过深 (10 层)，影响可读性",
      "severity": "medium",
      "confidence": 0.75,
      "effort": "low",
      "impact": "maintainability",
      "file_path": "src\\core\\business_process\\optimizer\\components\\decision_engine.py",
      "line_number": 279,
      "code_snippet": "analysis: Any) -> DecisionResult:",
      "suggested_fix": "提取嵌套代码为独立函数，或使用早期返回",
      "risk_level": "low",
      "automated": true
    },
    {
      "opportunity_id": "deep_nesting_3135289770125234907_95",
      "title": "深层嵌套重构",
      "description": "代码嵌套过深 (10 层)，影响可读性",
      "severity": "medium",
      "confidence": 0.75,
      "effort": "low",
      "impact": "maintainability",
      "file_path": "src\\core\\business_process\\optimizer\\components\\performance_analyzer.py",
      "line_number": 96,
      "code_snippet": "context: Any) -> AnalysisResult:",
      "suggested_fix": "提取嵌套代码为独立函数，或使用早期返回",
      "risk_level": "low",
      "automated": true
    },
    {
      "opportunity_id": "deep_nesting_3135289770125234907_178",
      "title": "深层嵌套重构",
      "description": "代码嵌套过深 (9 层)，影响可读性",
      "severity": "medium",
      "confidence": 0.75,
      "effort": "low",
      "impact": "maintainability",
      "file_path": "src\\core\\business_process\\optimizer\\components\\performance_analyzer.py",
      "line_number": 179,
      "code_snippet": "metrics: Dict[str, Any]) -> List[str]:",
      "suggested_fix": "提取嵌套代码为独立函数，或使用早期返回",
      "risk_level": "low",
      "automated": true
    },
    {
      "opportunity_id": "deep_nesting_3135289770125234907_205",
      "title": "深层嵌套重构",
      "description": "代码嵌套过深 (10 层)，影响可读性",
      "severity": "medium",
      "confidence": 0.75,
      "effort": "low",
      "impact": "maintainability",
      "file_path": "src\\core\\business_process\\optimizer\\components\\performance_analyzer.py",
      "line_number": 206,
      "code_snippet": "insights: List[str]) -> List[str]:",
      "suggested_fix": "提取嵌套代码为独立函数，或使用早期返回",
      "risk_level": "low",
      "automated": true
    },
    {
      "opportunity_id": "deep_nesting_3135289770125234907_241",
      "title": "深层嵌套重构",
      "description": "代码嵌套过深 (10 层)，影响可读性",
      "severity": "medium",
      "confidence": 0.75,
      "effort": "low",
      "impact": "maintainability",
      "file_path": "src\\core\\business_process\\optimizer\\components\\performance_analyzer.py",
      "line_number": 242,
      "code_snippet": "insights: List[str]) -> List[str]:",
      "suggested_fix": "提取嵌套代码为独立函数，或使用早期返回",
      "risk_level": "low",
      "automated": true
    },
    {
      "opportunity_id": "deep_nesting_-2724420683521343566_67",
      "title": "深层嵌套重构",
      "description": "代码嵌套过深 (7 层)，影响可读性",
      "severity": "medium",
      "confidence": 0.75,
      "effort": "low",
      "impact": "maintainability",
      "file_path": "src\\core\\business_process\\optimizer\\components\\process_executor.py",
      "line_number": 68,
      "code_snippet": "decision_engine: Any) -> ExecutionResult:",
      "suggested_fix": "提取嵌套代码为独立函数，或使用早期返回",
      "risk_level": "low",
      "automated": true
    },
    {
      "opportunity_id": "deep_nesting_-2724420683521343566_145",
      "title": "深层嵌套重构",
      "description": "代码嵌套过深 (6 层)，影响可读性",
      "severity": "medium",
      "confidence": 0.75,
      "effort": "low",
      "impact": "maintainability",
      "file_path": "src\\core\\business_process\\optimizer\\components\\process_executor.py",
      "line_number": 146,
      "code_snippet": "decision_engine: Any) -> Dict[str, Any]:",
      "suggested_fix": "提取嵌套代码为独立函数，或使用早期返回",
      "risk_level": "low",
      "automated": true
    },
    {
      "opportunity_id": "deep_nesting_-2724420683521343566_212",
      "title": "深层嵌套重构",
      "description": "代码嵌套过深 (8 层)，影响可读性",
      "severity": "medium",
      "confidence": 0.75,
      "effort": "low",
      "impact": "maintainability",
      "file_path": "src\\core\\business_process\\optimizer\\components\\process_executor.py",
      "line_number": 213,
      "code_snippet": "decision_engine: Any) -> ExecutionResult:",
      "suggested_fix": "提取嵌套代码为独立函数，或使用早期返回",
      "risk_level": "low",
      "automated": true
    },
    {
      "opportunity_id": "deep_nesting_-2724420683521343566_233",
      "title": "深层嵌套重构",
      "description": "代码嵌套过深 (7 层)，影响可读性",
      "severity": "medium",
      "confidence": 0.75,
      "effort": "low",
      "impact": "maintainability",
      "file_path": "src\\core\\business_process\\optimizer\\components\\process_executor.py",
      "line_number": 234,
      "code_snippet": "decision_engine: Any) -> ExecutionResult:",
      "suggested_fix": "提取嵌套代码为独立函数，或使用早期返回",
      "risk_level": "low",
      "automated": true
    },
    {
      "opportunity_id": "deep_nesting_-5947762189228750654_85",
      "title": "深层嵌套重构",
      "description": "代码嵌套过深 (9 层)，影响可读性",
      "severity": "medium",
      "confidence": 0.75,
      "effort": "low",
      "impact": "maintainability",
      "file_path": "src\\core\\business_process\\optimizer\\components\\recommendation_generator.py",
      "line_number": 86,
      "code_snippet": "analysis: Any,",
      "suggested_fix": "提取嵌套代码为独立函数，或使用早期返回",
      "risk_level": "low",
      "automated": true
    },
    {
      "opportunity_id": "deep_nesting_-5947762189228750654_86",
      "title": "深层嵌套重构",
      "description": "代码嵌套过深 (9 层)，影响可读性",
      "severity": "medium",
      "confidence": 0.75,
      "effort": "low",
      "impact": "maintainability",
      "file_path": "src\\core\\business_process\\optimizer\\components\\recommendation_generator.py",
      "line_number": 87,
      "code_snippet": "execution: Any) -> List[Recommendation]:",
      "suggested_fix": "提取嵌套代码为独立函数，或使用早期返回",
      "risk_level": "low",
      "automated": true
    },
    {
      "opportunity_id": "deep_nesting_-5947762189228750654_133",
      "title": "深层嵌套重构",
      "description": "代码嵌套过深 (10 层)，影响可读性",
      "severity": "medium",
      "confidence": 0.75,
      "effort": "low",
      "impact": "maintainability",
      "file_path": "src\\core\\business_process\\optimizer\\components\\recommendation_generator.py",
      "line_number": 134,
      "code_snippet": "stage_result: Dict[str, Any]) -> Optional[Recommendation]:",
      "suggested_fix": "提取嵌套代码为独立函数，或使用早期返回",
      "risk_level": "low",
      "automated": true
    }
  ],
  "opportunities_count": 167,
  "patterns_count": 345,
  "execution_plan_steps": 50,
  "organization_analysis": {
    "metrics": {
      "total_files": 19,
      "total_lines": 5695,
      "avg_file_size": 299.7368421052632,
      "max_file_size": 869,
      "largest_file": "demo.py",
      "quality_score": 0.88
    },
    "issues_count": 2,
    "recommendations_count": 12,
    "categories": {
      "core": [
        "__init__.py"
      ],
      "orchestration": [
        "config.py",
        "enums.py",
        "demo.py",
        "models.py",
        "business_process_models.py",
        "monitor.py",
        "state_machine.py"
      ],
      "integration": [
        "integration.py"
      ],
      "optimization": [
        "decision_engine.py",
        "performance_analyzer.py",
        "process_executor.py",
        "process_monitor.py",
        "recommendation_generator.py",
        "optimizer_configs.py",
        "models.py",
        "optimizer_refactored.py",
        "market_analyzer.py",
        "models.py"
      ]
    }
  }
}