{
  "technical_team_training": {
    "training_period": "6月15日-6月25日",
    "participants": {
      "total_participants": 25,
      "roles": {
        "backend_developers": 10,
        "frontend_developers": 5,
        "data_scientists": 4,
        "devops_engineers": 3,
        "system_architects": 3
      },
      "experience_levels": {
        "senior": 8,
        "mid_level": 12,
        "junior": 5
      }
    },
    "training_modules": {
      "system_architecture": {
        "participants": 25,
        "completion_rate": "100%",
        "average_score": 92,
        "satisfaction_score": 4.8,
        "status": "completed"
      },
      "api_development": {
        "participants": 15,
        "completion_rate": "100%",
        "average_score": 88,
        "satisfaction_score": 4.6,
        "status": "completed"
      },
      "machine_learning_pipeline": {
        "participants": 12,
        "completion_rate": "100%",
        "average_score": 85,
        "satisfaction_score": 4.7,
        "status": "completed"
      },
      "kubernetes_deployment": {
        "participants": 8,
        "completion_rate": "100%",
        "average_score": 90,
        "satisfaction_score": 4.9,
        "status": "completed"
      },
      "security_best_practices": {
        "participants": 25,
        "completion_rate": "100%",
        "average_score": 94,
        "satisfaction_score": 4.8,
        "status": "completed"
      }
    },
    "training_methods": {
      "instructor_led": {
        "sessions": 15,
        "total_hours": 60,
        "participants": 25,
        "effectiveness": "95%"
      },
      "hands_on_labs": {
        "sessions": 20,
        "total_hours": 80,
        "participants": 25,
        "completion_rate": "98%"
      },
      "video_tutorials": {
        "videos": 25,
        "total_views": 425,
        "average_rating": 4.7,
        "completion_rate": "85%"
      },
      "peer_learning": {
        "study_groups": 5,
        "total_hours": 40,
        "participants": 20,
        "effectiveness": "90%"
      }
    },
    "assessment_results": {
      "knowledge_assessment": {
        "participants": 25,
        "average_score": 89.2,
        "passing_rate": "96%",
        "improvement_rate": "85%"
      },
      "skill_assessment": {
        "participants": 25,
        "average_score": 87.5,
        "passing_rate": "92%",
        "competency_gain": "80%"
      },
      "project_assessment": {
        "projects": 8,
        "average_score": 91.0,
        "passing_rate": "100%",
        "code_quality": "88%"
      }
    },
    "training_effectiveness": {
      "learning_objectives": {
        "achieved": 45,
        "total": 50,
        "achievement_rate": "90%"
      },
      "skill_improvement": {
        "baseline_score": 65.5,
        "final_score": 87.2,
        "improvement": "21.7分"
      },
      "knowledge_retention": {
        "immediate_retention": "85%",
        "one_month_retention": "78%",
        "three_month_retention": "72%"
      },
      "practical_application": {
        "training_projects": 8,
        "successful_deployments": 8,
        "production_contribution": "显著"
      }
    },
    "certification": {
      "certificates_issued": 24,
      "certification_levels": {
        "expert": 3,
        "advanced": 8,
        "intermediate": 10,
        "basic": 3
      },
      "validity_period": "2年",
      "renewal_requirements": "继续教育 + 技能评估"
    },
    "training_summary": {
      "total_training_hours": 180,
      "total_participants": 25,
      "overall_satisfaction": 4.75,
      "knowledge_gain": "89.2%",
      "skill_improvement": "80%",
      "certification_rate": "96%",
      "production_readiness": "95%"
    }
  }
}